luma/led_matrix/__init__.py
luma/led_matrix/const.py
luma/led_matrix/device.py
luma/led_matrix/segment_mapper.py
luma.led_matrix-1.7.1.dist-info/LICENSE.rst
luma.led_matrix-1.7.1.dist-info/METADATA
luma.led_matrix-1.7.1.dist-info/WHEEL
luma.led_matrix-1.7.1.dist-info/top_level.txt
luma.led_matrix-1.7.1.dist-info/RECORD
