Metadata-Version: 2.1
Name: luma.led_matrix
Version: 1.7.1
Summary: A library to drive a MAX7219 LED serializer (using SPI) and WS2812 NeoPixels (using DMA)
Home-page: https://github.com/rm-hull/luma.led_matrix
Author: Richard Hull
Author-email: richard.hull@destructuring-bind.org
License: MIT
Keywords: raspberry pi,rpi,led,max7219,matrix,seven segment,7 segment,neopixel,neosegment,ws2812,ws281x,apa102,unicorn-phat,unicorn-hat,unicorn-hat-hd
Classifier: License :: OSI Approved :: MIT License
Classifier: Development Status :: 5 - Production/Stable
Classifier: Intended Audience :: Education
Classifier: Intended Audience :: Developers
Classifier: Topic :: Education
Classifier: Topic :: System :: Hardware
Classifier: Topic :: System :: Hardware :: Hardware Drivers
Classifier: Programming Language :: Python :: 3
Classifier: Programming Language :: Python :: 3.7
Classifier: Programming Language :: Python :: 3.8
Classifier: Programming Language :: Python :: 3.9
Classifier: Programming Language :: Python :: 3.10
Classifier: Programming Language :: Python :: 3.11
Classifier: Programming Language :: Python :: 3.12
Requires-Python: <4,>=3.7
License-File: LICENSE.rst
Requires-Dist: luma.core>=2.4.0
Requires-Dist: rpi_ws281x; platform_machine == "armv7l" and platform_system == "Linux"
Provides-Extra: docs
Requires-Dist: sphinx>=1.5.1; extra == "docs"
Requires-Dist: sphinx-rtd-theme; extra == "docs"
Provides-Extra: qa
Requires-Dist: flake8; extra == "qa"
Requires-Dist: rstcheck; extra == "qa"
Provides-Extra: test
Requires-Dist: pytest; extra == "test"
Requires-Dist: pytest-cov; extra == "test"
Requires-Dist: pytest-timeout; extra == "test"
